ImageEngine/__init__.py
ImageEngine/main.py
ImageEngine/search_bing.py
ImageEngine/search_duckduckgo.py
ImageEngine/search_google.py
ImageEngine/search_web.py
ImageEngine-0.2.5.dist-info/LICENSE
ImageEngine-0.2.5.dist-info/METADATA
ImageEngine-0.2.5.dist-info/WHEEL
ImageEngine-0.2.5.dist-info/entry_points.txt
ImageEngine-0.2.5.dist-info/top_level.txt
ImageEngine-0.2.5.dist-info/RECORD
