Metadata-Version: 2.1
Name: ImageEngine
Version: 0.2.5
Summary: A package to download images from various search engines.
Author: Jay Punekar
Author-email: jay.punekar@icloud.com
License: MIT
License-File: LICENSE
Requires-Dist: fastai
Requires-Dist: duckduckgo-search
Requires-Dist: icrawler
Requires-Dist: requests
Requires-Dist: Pillow
Requires-Dist: torch ==2.3.0
Requires-Dist: torchvision ==0.18.0
Requires-Dist: torchaudio ==2.3.0
